parserclass/__init__.py
parserclass/errors.py
parserclass/types.py
parserclass/_vendor/__init__.py
parserclass/_vendor/retrieveableset/__init__.py
parserclass-0.1.0a8.dist-info/METADATA
parserclass-0.1.0a8.dist-info/WHEEL
parserclass-0.1.0a8.dist-info/top_level.txt
parserclass-0.1.0a8.dist-info/RECORD
